MANIFEST.in
setup.py
kodiswift/__init__.py
kodiswift/actions.py
kodiswift/common.py
kodiswift/constants.py
kodiswift/listitem.py
kodiswift/logger.py
kodiswift/module.py
kodiswift/plugin.py
kodiswift/request.py
kodiswift/storage.py
kodiswift/urls.py
kodiswift/xbmcmixin.py
kodiswift.egg-info/PKG-INFO
kodiswift.egg-info/SOURCES.txt
kodiswift.egg-info/dependency_links.txt
kodiswift.egg-info/entry_points.txt
kodiswift.egg-info/top_level.txt
kodiswift/cli/__init__.py
kodiswift/cli/app.py
kodiswift/cli/cli.py
kodiswift/cli/console.py
kodiswift/cli/create.py
kodiswift/cli/data/addon.py
kodiswift/cli/data/addon.xml
kodiswift/cli/data/resources/__init__.py
kodiswift/cli/data/resources/language/English/strings.po
kodiswift/cli/data/resources/lib/__init__.py
kodiswift/mockxbmc/__init__.py
kodiswift/mockxbmc/polib.py
kodiswift/mockxbmc/utils.py
kodiswift/mockxbmc/xbmc.py
kodiswift/mockxbmc/xbmcaddon.py
kodiswift/mockxbmc/xbmcgui.py
kodiswift/mockxbmc/xbmcplugin.py
kodiswift/mockxbmc/xbmcvfs.py