Metadata-Version: 1.1
Name: kodiswift
Version: 0.0.7
Summary: A micro framework for rapid development of Kodi plugins.
Home-page: https://github.com/Sinap/kodiswift
Author: Aaron Frase
Author-email: afrase91@gmail.com
License: GPL3
Keywords: example documentation tutorial
Platform: UNKNOWN
Classifier: Development Status :: 3 - Alpha
Classifier: Intended Audience :: Developers
Classifier: License :: OSI Approved :: GNU Affero General Public License v3
Classifier: Natural Language :: English
Classifier: Topic :: Utilities
Classifier: Programming Language :: Python :: 2
Classifier: Programming Language :: Python :: 2.7
